{"reference":"hafs","surah":63,"hafsVSwarsh":{"diffCount":299,"diffs":[[0,"إِذَا جَآءَكَ "],[-1,"ٱ"],[1,"اَ"],[0,"ل"],[-1,"ۡ"],[1,"ْ"],[0,"مُنَٰفِقُونَ قَالُواْ نَش"],[-1,"ۡ"],[1,"ْ"],[0,"هَدُ إِنَّكَ لَرَسُولُ "],[-1,"ٱ"],[1,"اُ"],[0,"للَّهِ وَ"],[-1,"ٱ"],[1,"ا"],[0,"للَّهُ يَع"],[-1,"ۡ"],[1,"ْ"],[0,"لَمُ إِنَّكَ لَرَسُولُهُ وَ"],[-1,"ٱ"],[1,"ا"],[0,"للَّهُ يَش"],[-1,"ۡ"],[1,"ْ"],[0,"هَدُ إِنَّ "],[-1,"ٱ"],[1,"اَ"],[0,"ل"],[-1,"ۡ"],[1,"ْ"],[0,"مُنَٰفِقِينَ لَكَٰذِبُونَ "],[-1,"ٱ"],[1,"اَ"],[0,"تَّخَذُوٓاْ أَي"],[-1,"ۡ"],[1,"ْ"],[0,"مَٰنَهُم"],[-1,"ۡ"],[1,"ْ"],[0," جُنَّةٗ فَصَدُّواْ عَن سَبِيلِ "],[-1,"ٱ"],[1,"اِ"],[0,"للَّهِ إِنَّهُم"],[-1,"ۡ"],[1,"ْ"],[0," سَآءَ مَا كَانُواْ يَع"],[-1,"ۡ"],[1,"ْ"],[0,"مَلُونَ ذَٰلِكَ بِأَنَّهُم"],[-1,"ۡ"],[1,"ُٓ"],[0," ءَامَنُواْ ثُمَّ كَفَرُواْ فَطُبِعَ عَلَ"],[-1,"ى"],[1,"ي"],[0,"ٰ قُلُوبِهِم"],[-1,"ۡ"],[1,"ْ"],[0," فَهُم"],[-1,"ۡ"],[1,"ْ"],[0," لَا يَف"],[-1,"ۡ"],[1,"ْ"],[0,"قَهُونَ وَإِذَا رَأَي"],[-1,"ۡ"],[1,"ْ"],[0,"تَهُم"],[-1,"ۡ"],[1,"ْ"],[0," تُع"],[-1,"ۡ"],[1,"ْ"],[0,"جِبُكَ أَج"],[-1,"ۡ"],[1,"ْ"],[0,"سَامُهُم"],[-1,"ۡ"],[1,"ْ"],[0," وَإِن"],[1,"ْ"],[0," ي"],[1,"ّ"],[0,"َقُولُواْ تَس"],[-1,"ۡ"],[1,"ْ"],[0,"مَع"],[-1,"ۡ"],[1,"ْ"],[0," لِقَو"],[-1,"ۡ"],[1,"ْ"],[0,"لِهِم"],[-1,"ۡ"],[1,"ْ"],[0," كَأَنَّهُم"],[-1,"ۡ"],[1,"ْ"],[0," خُشُبٞ مُّسَنَّدَةٞ يَح"],[-1,"ۡ"],[1,"ْ"],[0,"س"],[-1,"َ"],[1,"ِ"],[0,"بُونَ كُلَّ صَي"],[-1,"ۡ"],[1,"ْ"],[0,"حَةٍ عَلَي"],[-1,"ۡ"],[1,"ْ"],[0,"هِم"],[-1,"ۡ"],[1,"ْ"],[0," هُمُ "],[-1,"ٱ"],[1,"اُ"],[0,"ل"],[-1,"ۡ"],[1,"ْ"],[0,"عَدُوُّ فَ"],[-1,"ٱ"],[1,"ا"],[0,"ح"],[-1,"ۡ"],[1,"ْ"],[0,"ذَر"],[-1,"ۡ"],[1,"ْ"],[0,"هُم"],[-1,"ۡ"],[1,"ْ"],[0," قَٰتَلَهُمُ "],[-1,"ٱ"],[1,"اُ"],[0,"للَّهُ أَنّ"],[-1,"َى"],[1,"ي"],[0,"ٰ يُ"],[-1,"ؤۡ"],[1,"و"],[0,"فَكُونَ وَإِذَا قِيلَ لَهُم"],[-1,"ۡ"],[1,"ْ"],[0," تَعَالَو"],[-1,"ۡ"],[1,"ْ"],[0,"اْ يَس"],[-1,"ۡ"],[1,"ْ"],[0,"تَغ"],[-1,"ۡ"],[1,"ْ"],[0,"فِر"],[-1,"ۡ"],[1,"ْ"],[0," لَكُم"],[-1,"ۡ"],[1,"ْ"],[0," رَسُولُ "],[-1,"ٱ"],[1,"اُ"],[0,"للَّهِ لَو"],[-1,"ّ"],[0,"َو"],[-1,"ۡ"],[1,"ْ"],[0,"اْ رُءُوسَهُم"],[-1,"ۡ"],[1,"ْ"],[0," وَرَأَي"],[-1,"ۡ"],[1,"ْ"],[0,"تَهُم"],[-1,"ۡ"],[1,"ْ"],[0," يَصُدُّونَ وَهُم مُّس"],[-1,"ۡ"],[1,"ْ"],[0,"تَك"],[-1,"ۡ"],[1,"ْ"],[0,"بِرُونَ سَوَآءٌ عَلَي"],[-1,"ۡ"],[1,"ْ"],[0,"هِم"],[-1,"ۡ"],[1,"ُٓ"],[0," أَس"],[-1,"ۡ"],[1,"ْ"],[0,"تَغ"],[-1,"ۡ"],[1,"ْ"],[0,"فَر"],[-1,"ۡ"],[1,"ْ"],[0,"تَ لَهُم"],[-1,"ۡ"],[1,"ُٓ"],[0," أَم"],[-1,"ۡ"],[1,"ْ"],[0," لَم"],[-1,"ۡ"],[1,"ْ"],[0," تَس"],[-1,"ۡ"],[1,"ْ"],[0,"تَغ"],[-1,"ۡ"],[1,"ْ"],[0,"فِر"],[-1,"ۡ"],[1,"ْ"],[0," لَهُم"],[-1,"ۡ"],[1,"ْ"],[0," لَن"],[1,"ْ"],[0," ي"],[1,"ّ"],[0,"َغ"],[-1,"ۡ"],[1,"ْ"],[0,"فِرَ "],[-1,"ٱ"],[1,"اَ"],[0,"للَّهُ لَهُم"],[-1,"ۡ"],[1,"ُٓ"],[0," إِنَّ "],[-1,"ٱ"],[1,"اَ"],[0,"للَّهَ لَا يَه"],[-1,"ۡ"],[1,"ْ"],[0,"دِ"],[-1,"ي"],[1,"ے"],[0," "],[-1,"ٱ"],[1,"اِ"],[0,"ل"],[-1,"ۡ"],[1,"ْ"],[0,"قَو"],[-1,"ۡ"],[1,"ْ"],[0,"مَ "],[-1,"ٱ"],[1,"اَ"],[0,"ل"],[-1,"ۡ"],[1,"ْ"],[0,"فَٰسِقِينَ هُمُ "],[-1,"ٱ"],[1,"اُ"],[0,"ل"],[-1,"َّ"],[0,"ذِينَ يَقُولُونَ لَا تُنفِقُواْ عَلَ"],[-1,"ى"],[1,"ي"],[0,"ٰ مَن"],[-1,"ۡ"],[1,"ْ"],[0," عِندَ رَسُولِ "],[-1,"ٱ"],[1,"اِ"],[0,"للَّهِ حَتَّ"],[-1,"ى"],[1,"ي"],[0,"ٰ يَنفَضُّواْ وَلِل"],[-1,"َّ"],[0,"هِ خَزَآئِنُ "],[-1,"ٱ"],[1,"اُ"],[0,"لسَّمَٰوَٰتِ وَ"],[-1,"ٱ"],[1,"ا"],[0,"ل"],[-1,"ۡأ"],[0,"َ"],[1,"ا"],[0,"ر"],[-1,"ۡ"],[1,"ْ"],[0,"ضِ وَلَٰكِنَّ "],[-1,"ٱ"],[1,"اَ"],[0,"ل"],[-1,"ۡ"],[1,"ْ"],[0,"مُنَٰفِقِينَ لَا يَف"],[-1,"ۡ"],[1,"ْ"],[0,"قَهُونَ يَقُولُونَ لَئِن رَّجَع"],[-1,"ۡ"],[1,"ْ"],[0,"نَآ إِلَ"],[-1,"ى"],[1,"ي"],[0," "],[-1,"ٱ"],[1,"اَ"],[0,"ل"],[-1,"ۡ"],[1,"ْ"],[0,"مَدِينَةِ لَيُخ"],[-1,"ۡ"],[1,"ْ"],[0,"رِجَنَّ "],[-1,"ٱ"],[1,"اَ"],[0,"ل"],[-1,"ۡأ"],[0,"َ"],[1,"ا"],[0,"عَزُّ مِن"],[-1,"ۡ"],[1,"ْ"],[0,"هَا "],[-1,"ٱ"],[1,"اَ"],[0,"ل"],[-1,"ۡأ"],[0,"َ"],[1,"ا"],[0,"ذَلَّ وَلِل"],[-1,"َّ"],[0,"هِ "],[-1,"ٱ"],[1,"اِ"],[0,"ل"],[-1,"ۡ"],[1,"ْ"],[0,"عِزَّةُ وَلِرَسُولِهِ وَلِل"],[-1,"ۡ"],[1,"ْ"],[0,"مُ"],[-1,"ؤۡ"],[1,"و"],[0,"مِنِينَ وَلَٰكِنَّ "],[-1,"ٱ"],[1,"اَ"],[0,"ل"],[-1,"ۡ"],[1,"ْ"],[0,"مُنَٰفِقِينَ لَا يَع"],[-1,"ۡ"],[1,"ْ"],[0,"لَمُونَ يَٰٓأَيُّهَا "],[-1,"ٱ"],[1,"اَ"],[0,"ل"],[-1,"َّ"],[0,"ذِينَ ءَامَنُواْ لَا تُل"],[-1,"ۡ"],[1,"ْ"],[0,"هِكُم"],[-1,"ۡ"],[1,"ُٓ"],[0," أَم"],[-1,"ۡ"],[1,"ْ"],[0,"وَٰلُكُم"],[-1,"ۡ"],[1,"ْ"],[0," وَلَآ أَو"],[-1,"ۡ"],[1,"ْ"],[0,"لَٰدُكُم"],[-1,"ۡ"],[1,"ْ"],[0," عَن ذِك"],[-1,"ۡ"],[1,"ْ"],[0,"رِ "],[-1,"ٱ"],[1,"اِ"],[0,"للَّهِ وَمَن"],[1,"ْ"],[0," ي"],[1,"ّ"],[0,"َف"],[-1,"ۡ"],[1,"ْ"],[0,"عَل"],[-1,"ۡ"],[1,"ْ"],[0," ذَٰلِكَ فَأُوْلَٰٓئِكَ هُمُ "],[-1,"ٱ"],[1,"اُ"],[0,"ل"],[-1,"ۡ"],[1,"ْ"],[0,"خَٰسِرُونَ وَأَنفِقُواْ مِن مَّا رَزَق"],[-1,"ۡ"],[1,"ْ"],[0,"نَٰكُم مِّن قَب"],[-1,"ۡ"],[1,"ْ"],[0,"لِ أَن"],[1,"ْ"],[0," ي"],[1,"ّ"],[0,"َ"],[-1,"أۡ"],[1,"ا"],[0,"تِيَ أَحَدَكُمُ "],[-1,"ٱ"],[1,"اُ"],[0,"ل"],[-1,"ۡ"],[1,"ْ"],[0,"مَو"],[-1,"ۡ"],[1,"ْ"],[0,"تُ فَيَقُولَ رَبِّ لَو"],[-1,"ۡ"],[1,"ْ"],[0,"لَآ أَخَّر"],[-1,"ۡ"],[1,"ْ"],[0,"تَنِ"],[-1,"ي"],[1,"ے"],[0,"ٓ إِلَ"],[-1,"ى"],[1,"ي"],[0,"ٰٓ أَجَلٖ قَرِيبٖ فَأَصَّدَّقَ وَأَكُن مِّنَ "],[-1,"ٱ"],[1,"اَ"],[0,"لصَّٰلِحِينَ وَلَن"],[1,"ْ"],[0," ي"],[1,"ّ"],[0,"ُ"],[-1,"ؤ"],[1,"و"],[0,"َخِّرَ "],[-1,"ٱ"],[1,"اَ"],[0,"للَّهُ نَف"],[-1,"ۡ"],[1,"ْ"],[0,"س"],[1,"ا"],[0,"ً"],[-1,"ا"],[0," "],[-1,"إ"],[1,"ا"],[0,"ِذَا جَآءَ "],[-1,"أَ"],[1,"ا"],[0,"جَلُهَا وَ"],[-1,"ٱ"],[1,"ا"],[0,"للَّهُ خَبِيرُ بِمَا تَع"],[-1,"ۡ"],[1,"ْ"],[0,"مَلُونَ"]]},"hafsVSdoori":{"diffCount":77,"diffs":[[0,"إِذَا جَآءَكَ "],[-1,"ٱ"],[1,"اَ"],[0,"لۡمُنَٰفِقُونَ قَالُواْ نَشۡهَدُ إِنَّكَ لَرَسُولُ "],[-1,"ٱ"],[1,"اُ"],[0,"للَّهِ وَ"],[-1,"ٱ"],[1,"اَ"],[0,"للَّهُ يَعۡلَمُ إِنَّكَ لَرَسُولُهُ وَ"],[-1,"ٱ"],[1,"اَ"],[0,"للَّهُ يَشۡهَدُ إِنَّ "],[-1,"ٱ"],[1,"اَ"],[0,"لۡمُنَٰفِقِينَ لَكَٰذِبُونَ "],[-1,"ٱ"],[1,"اَ"],[0,"تَّخَذُوٓاْ أَيۡمَٰنَهُمۡ جُنَّةٗ فَصَدُّواْ عَن سَبِيلِ "],[-1,"ٱ"],[1,"اِ"],[0,"للَّهِ إِنَّهُمۡ سَآءَ مَا كَانُواْ يَعۡمَلُونَ ذَٰلِكَ بِأَنَّهُمۡ ءَامَنُواْ ثُمَّ كَفَرُواْ فَطُبِعَ عَلَىٰ قُلُوبِهِمۡ فَهُمۡ لَا يَفۡقَهُونَ وَإِذَا رَأَيۡتَهُمۡ تُعۡجِبُكَ أَجۡسَامُهُمۡ وَإِن يَقُولُواْ تَسۡمَعۡ لِقَوۡلِهِمۡ كَأَنَّهُمۡ خُش"],[-1,"ُ"],[1,"ۡ"],[0,"بٞ مُّسَنَّدَةٞ يَحۡس"],[-1,"َ"],[1,"ِ"],[0,"بُونَ كُلَّ صَيۡحَةٍ عَلَيۡهِمۡ هُمُ "],[-1,"ٱ"],[1,"اُ"],[0,"لۡعَدُوُّ فَ"],[-1,"ٱ"],[1,"اَ"],[0,"حۡذَرۡهُمۡ قَٰتَلَهُمُ "],[-1,"ٱ"],[1,"اُ"],[0,"للَّهُ أَنّ"],[-1,"َى"],[1,"ي"],[0,"ٰ يُؤۡفَكُونَ وَإِذَا قِيلَ لَهُمۡ تَعَالَوۡاْ يَسۡتَغۡفِر"],[-1,"ۡ"],[0," ل"],[1,"ّ"],[0,"َكُمۡ رَسُولُ "],[-1,"ٱ"],[1,"اُ"],[0,"للَّهِ لَوَّوۡاْ رُءُوسَهُمۡ وَرَأَيۡتَهُمۡ يَصُدُّونَ وَهُم مُّسۡتَكۡبِرُونَ سَوَآءٌ عَلَيۡهِمۡ أَسۡتَغۡفَرۡتَ لَهُمۡ أَمۡ لَمۡ تَسۡتَغۡفِر"],[-1,"ۡ"],[0," ل"],[1,"ّ"],[0,"َهُمۡ لَن يَغۡفِرَ "],[-1,"ٱ"],[1,"اَ"],[0,"للَّهُ لَهُمۡ إِنَّ "],[-1,"ٱ"],[1,"اَ"],[0,"للَّهَ لَا يَهۡدِي "],[-1,"ٱ"],[1,"اِ"],[0,"لۡقَوۡمَ "],[-1,"ٱ"],[1,"اَ"],[0,"لۡفَٰسِقِينَ هُمُ "],[-1,"ٱ"],[1,"اُ"],[0,"لَّذِينَ يَقُولُونَ لَا تُنفِقُواْ عَلَىٰ مَنۡ عِندَ رَسُولِ "],[-1,"ٱ"],[1,"اِ"],[0,"للَّهِ حَتَّىٰ يَنفَضُّواْ وَلِلَّهِ خَزَآئِنُ "],[-1,"ٱ"],[1,"اُ"],[0,"لسَّمَٰوَٰتِ وَ"],[-1,"ٱ"],[1,"اَ"],[0,"لۡأَرۡضِ وَلَٰكِنَّ "],[-1,"ٱ"],[1,"اَ"],[0,"لۡمُنَٰفِقِينَ لَا يَفۡقَهُونَ يَقُولُونَ لَئِن رَّجَعۡنَآ إِلَى "],[-1,"ٱ"],[1,"اَ"],[0,"لۡمَدِينَةِ لَيُخۡرِجَنَّ "],[-1,"ٱ"],[1,"اَ"],[0,"لۡأَعَزُّ مِنۡهَا "],[-1,"ٱ"],[1,"اَ"],[0,"لۡأَذَلَّ وَلِلَّهِ "],[-1,"ٱ"],[1,"اِ"],[0,"لۡعِزَّةُ وَلِرَسُولِهِ وَلِلۡمُؤۡمِنِينَ وَلَٰكِنَّ "],[-1,"ٱ"],[1,"اَ"],[0,"لۡمُنَٰفِقِينَ لَا يَعۡلَمُونَ يَٰٓأَيُّهَا "],[-1,"ٱ"],[1,"اَ"],[0,"لَّذِينَ ءَامَنُواْ لَا تُلۡهِكُمۡ أَمۡوَٰلُكُمۡ وَلَآ أَوۡلَٰدُكُمۡ عَن ذِكۡرِ "],[-1,"ٱ"],[1,"اِ"],[0,"للَّهِ وَمَن يَفۡعَلۡ ذَٰلِكَ فَأُوْلَٰٓئِكَ هُمُ "],[-1,"ٱ"],[1,"اُ"],[0,"لۡخَٰسِرُونَ وَأَنفِقُواْ مِن مَّا رَزَقۡنَٰكُم مِّن قَبۡلِ أَن يَأۡتِيَ أَحَدَكُمُ "],[-1,"ٱ"],[1,"اُ"],[0,"لۡمَوۡتُ فَيَقُولَ رَبِّ لَوۡلَآ أَخَّرۡتَنِيٓ إِلَىٰٓ أَجَلٖ قَرِيبٖ فَأَصَّدَّقَ وَأَكُن"],[1,"َ"],[0," م"],[-1,"ّ"],[0,"ِنَ "],[-1,"ٱ"],[1,"اَ"],[0,"لصَّٰلِحِينَ وَلَن يُؤَخِّرَ "],[-1,"ٱ"],[1,"اَ"],[0,"للَّهُ نَفۡسًا إِذَا جَآ"],[-1,"ءَ"],[0," أَجَلُهَا وَ"],[-1,"ٱ"],[1,"اَ"],[0,"للَّهُ خَبِيرُ بِمَا تَعۡمَلُونَ"]]},"hafsVSsosi":{"diffCount":92,"diffs":[[0,"إِذَا جَآءَكَ "],[-1,"ٱ"],[1,"اَ"],[0,"لۡمُنَٰفِقُونَ قَالُواْ نَشۡهَدُ إِنَّكَ لَرَسُولُ "],[-1,"ٱ"],[1,"اُ"],[0,"للَّهِ وَ"],[-1,"ٱ"],[1,"اَ"],[0,"للَّهُ يَعۡلَمُ إِنَّكَ لَرَسُولُهُ وَ"],[-1,"ٱ"],[1,"اَ"],[0,"للَّهُ يَشۡهَدُ إِنَّ "],[-1,"ٱ"],[1,"اَ"],[0,"لۡمُنَٰفِقِينَ لَكَٰذِبُونَ "],[-1,"ٱ"],[1,"اَ"],[0,"تَّخَذُو"],[-1,"ٓ"],[0,"اْ أَيۡمَٰنَهُمۡ جُنَّةٗ فَصَدُّواْ عَن سَبِيلِ "],[-1,"ٱ"],[1,"اِ"],[0,"للَّهِ إِنَّهُمۡ سَآءَ مَا كَانُواْ يَعۡمَلُونَ ذَٰلِكَ بِأَنَّهُمۡ ءَامَنُواْ ثُمَّ كَفَرُواْ فَطُبِع"],[-1,"َ"],[0," ع"],[1,"ّ"],[0,"َلَىٰ قُلُوبِهِمۡ فَهُمۡ لَا يَفۡقَهُونَ وَإِذَا رَأَيۡتَهُمۡ تُعۡجِبُكَ أَجۡسَامُهُمۡ وَإِن يَقُولُواْ تَسۡمَعۡ لِقَوۡلِهِمۡ كَأَنَّهُمۡ خُش"],[-1,"ُ"],[1,"ۡ"],[0,"بٞ مُّسَنَّدَةٞ يَحۡس"],[-1,"َ"],[1,"ِ"],[0,"بُونَ كُلَّ صَيۡحَةٍ عَلَيۡهِمۡ هُمُ "],[-1,"ٱ"],[1,"اُ"],[0,"لۡعَدُوُّ فَ"],[-1,"ٱ"],[1,"اَ"],[0,"حۡذَرۡهُمۡ قَٰتَلَهُمُ "],[-1,"ٱ"],[1,"اُ"],[0,"للَّهُ أَنَّىٰ يُ"],[-1,"ؤۡ"],[1,"و"],[0,"فَكُونَ وَإِذَا قِيل"],[-1,"َ"],[0," ل"],[1,"ّ"],[0,"َهُمۡ تَعَالَوۡاْ يَسۡتَغۡفِر"],[-1,"ۡ"],[0," ل"],[1,"ّ"],[0,"َكُمۡ رَسُولُ "],[-1,"ٱ"],[1,"اُ"],[0,"للَّهِ لَوَّوۡاْ رُءُوسَهُمۡ وَرَأَيۡتَهُمۡ يَصُدُّونَ وَهُم مُّسۡتَكۡبِرُونَ سَوَآءٌ عَلَيۡهِمۡ أَسۡتَغۡفَرۡتَ لَهُمۡ أَمۡ لَمۡ تَسۡتَغۡفِر"],[-1,"ۡ"],[0," ل"],[1,"ّ"],[0,"َهُمۡ لَن يَغۡفِرَ "],[-1,"ٱ"],[1,"اَ"],[0,"للَّهُ لَهُمۡ إِنَّ "],[-1,"ٱ"],[1,"اَ"],[0,"للَّهَ لَا يَهۡدِي "],[-1,"ٱ"],[1,"اِ"],[0,"لۡقَوۡمَ "],[-1,"ٱ"],[1,"اَ"],[0,"لۡفَٰسِقِينَ هُمُ "],[-1,"ٱ"],[1,"اُ"],[0,"لَّذِينَ يَقُولُونَ لَا تُنفِقُواْ عَلَىٰ مَنۡ عِندَ رَسُولِ "],[-1,"ٱ"],[1,"اِ"],[0,"للَّهِ حَتَّىٰ يَنفَضُّواْ وَلِلَّهِ خَزَآئِنُ "],[-1,"ٱ"],[1,"اُ"],[0,"لسَّمَٰوَٰتِ وَ"],[-1,"ٱ"],[1,"اَ"],[0,"لۡأَرۡضِ وَلَٰكِنَّ "],[-1,"ٱ"],[1,"اَ"],[0,"لۡمُنَٰفِقِينَ لَا يَفۡقَهُونَ يَقُولُونَ لَئِن رَّجَعۡنَا"],[-1,"ٓ"],[0," إِلَى "],[-1,"ٱ"],[1,"اَ"],[0,"لۡمَدِينَةِ لَيُخۡرِجَنَّ "],[-1,"ٱ"],[1,"اَ"],[0,"لۡأَعَزُّ مِنۡهَا "],[-1,"ٱ"],[1,"اَ"],[0,"لۡأَذَلَّ وَلِلَّهِ "],[-1,"ٱ"],[1,"اِ"],[0,"لۡعِزَّةُ وَلِرَسُولِهِ وَلِلۡمُ"],[-1,"ؤۡ"],[1,"و"],[0,"مِنِينَ وَلَٰكِنَّ "],[-1,"ٱ"],[1,"اَ"],[0,"لۡمُنَٰفِقِينَ لَا يَعۡلَمُونَ يَٰ"],[-1,"ٓ"],[0,"أَيُّهَا "],[-1,"ٱ"],[1,"اَ"],[0,"لَّذِينَ ءَامَنُواْ لَا تُلۡهِكُمۡ أَمۡوَٰلُكُمۡ وَلَا"],[-1,"ٓ"],[0," أَوۡلَٰدُكُمۡ عَن ذِكۡرِ "],[-1,"ٱ"],[1,"اِ"],[0,"للَّهِ وَمَن يَفۡعَلۡ ذَٰلِكَ فَأُوْلَٰٓئِكَ هُمُ "],[-1,"ٱ"],[1,"اُ"],[0,"لۡخَٰسِرُونَ وَأَنفِقُواْ مِن مَّا رَزَقۡنَٰكُم مِّن قَبۡلِ أَن يَ"],[-1,"أۡ"],[1,"ا"],[0,"تِيَ أَحَدَكُمُ "],[-1,"ٱ"],[1,"اُ"],[0,"لۡمَوۡتُ فَيَقُولَ رَبِّ لَوۡلَا"],[-1,"ٓ"],[0," أَخَّرۡتَنِي"],[-1,"ٓ"],[0," إِلَىٰ"],[-1,"ٓ"],[0," أَجَلٖ قَرِيبٖ فَأَصَّدَّقَ وَأَكُن"],[1,"َ"],[0," م"],[-1,"ّ"],[0,"ِنَ "],[-1,"ٱ"],[1,"اَ"],[0,"لصَّٰلِحِينَ وَلَن يُؤَخِّرَ "],[-1,"ٱ"],[1,"اَ"],[0,"للَّهُ نَفۡسًا إِذَا جَا"],[-1,"ٓءَ"],[0," أَجَلُهَا وَ"],[-1,"ٱ"],[1,"اَ"],[0,"للَّهُ خَبِيرُ بِمَا تَعۡمَلُونَ"]]},"hafsVSqumbul":{"diffCount":61,"diffs":[[0,"إِذَا جَآءَكَ ٱلۡمُنَٰفِقُونَ قَالُواْ نَشۡهَدُ إِنَّكَ لَرَسُولُ ٱللَّهِ وَٱللَّهُ يَعۡلَمُ إِنَّكَ لَرَسُولُهُ وَٱللَّهُ يَشۡهَدُ إِنَّ ٱلۡمُنَٰفِقِينَ لَكَٰذِبُونَ ٱتَّخَذُو"],[-1,"ٓ"],[0,"اْ أَيۡمَٰنَهُم"],[-1,"ۡ"],[1,"ُ"],[0," جُنَّةٗ فَصَدُّواْ عَن سَبِيلِ ٱللَّهِ إِنَّهُم"],[-1,"ۡ"],[1,"ُ"],[0," سَآءَ مَا كَانُواْ يَعۡمَلُونَ ذَٰلِكَ بِأَنَّهُم"],[-1,"ۡ"],[1,"ُ"],[0," ءَامَنُواْ ثُمَّ كَفَرُواْ فَطُبِعَ عَلَىٰ قُلُوبِهِم"],[-1,"ۡ"],[1,"ُ"],[0," فَهُم"],[-1,"ۡ"],[1,"ُ"],[0," لَا يَفۡقَهُونَ وَإِذَا رَأَيۡتَهُم"],[-1,"ۡ"],[1,"ُ"],[0," تُعۡجِبُكَ أَجۡسَامُهُم"],[-1,"ۡ"],[1,"ُ"],[0," وَإِن يَقُولُواْ تَسۡمَعۡ لِقَوۡلِهِم"],[-1,"ۡ"],[1,"ُ"],[0," كَأَنَّهُم"],[-1,"ۡ"],[1,"ُ"],[0," خُش"],[-1,"ُ"],[1,"ۡ"],[0,"بٞ مُّسَنَّدَةٞ يَحۡس"],[-1,"َ"],[1,"ِ"],[0,"بُونَ كُلَّ صَيۡحَةٍ عَلَيۡهِم"],[-1,"ۡ"],[1,"ُ"],[0," هُمُ ٱلۡعَدُوُّ فَٱحۡذَرۡهُم"],[-1,"ۡ"],[1,"ُ"],[0," قَٰتَلَهُمُ ٱللَّهُ أَنَّىٰ يُؤۡفَكُونَ وَإِذَا قِيلَ لَهُم"],[-1,"ۡ"],[1,"ُ"],[0," تَعَالَوۡاْ يَسۡتَغۡفِرۡ لَكُم"],[-1,"ۡ"],[1,"ُ"],[0," رَسُولُ ٱللَّهِ لَوَّوۡاْ رُءُوسَهُم"],[-1,"ۡ"],[1,"ُ"],[0," وَرَأَيۡتَهُم"],[-1,"ۡ"],[1,"ُ"],[0," يَصُدُّونَ وَهُم"],[1,"ُ"],[0," م"],[-1,"ّ"],[0,"ُسۡتَكۡبِرُونَ سَوَآءٌ عَلَيۡهِم"],[-1,"ۡ"],[1,"ُ"],[0," أَسۡتَغۡفَرۡتَ لَهُم"],[-1,"ۡ"],[1,"ُ"],[0," أَمۡ لَمۡ تَسۡتَغۡفِرۡ لَهُم"],[-1,"ۡ"],[1,"ُ"],[0," لَن يَغۡفِرَ ٱللَّهُ لَهُم"],[-1,"ۡ"],[1,"ُ"],[0," إِنَّ ٱللَّهَ لَا يَهۡدِي ٱلۡقَوۡمَ ٱلۡفَٰسِقِينَ هُمُ ٱلَّذِينَ يَقُولُونَ لَا تُنفِقُواْ عَلَىٰ مَنۡ عِندَ رَسُولِ ٱللَّهِ حَتَّىٰ يَنفَضُّواْ وَلِلَّهِ خَزَآئِنُ ٱلسَّمَٰوَٰتِ وَٱلۡأَرۡضِ وَلَٰكِنَّ ٱلۡمُنَٰفِقِينَ لَا يَفۡقَهُونَ يَقُولُونَ لَئِن رَّجَعۡنَا"],[-1,"ٓ"],[0," إِلَى ٱلۡمَدِينَةِ لَيُخۡرِجَنَّ ٱلۡأَعَزُّ مِنۡهَا ٱلۡأَذَلَّ وَلِلَّهِ ٱلۡعِزَّةُ وَلِرَسُولِهِ وَلِلۡمُؤۡمِنِينَ وَلَٰكِنَّ ٱلۡمُنَٰفِقِينَ لَا يَعۡلَمُونَ يَٰ"],[-1,"ٓ"],[0,"أَيُّهَا ٱلَّذِينَ ءَامَنُواْ لَا تُلۡهِكُم"],[-1,"ۡ"],[1,"ُ"],[0," أَمۡوَٰلُكُم"],[-1,"ۡ"],[1,"ُ"],[0," وَلَا"],[-1,"ٓ"],[0," أَوۡلَٰدُكُم"],[-1,"ۡ"],[1,"ُ"],[0," عَن ذِكۡرِ ٱللَّهِ وَمَن يَفۡعَلۡ ذَٰلِكَ فَأُوْلَٰٓئِكَ هُمُ ٱلۡخَٰسِرُونَ وَأَنفِقُواْ مِن مَّا رَزَقۡنَٰكُم"],[1,"ُ"],[0," م"],[-1,"ّ"],[0,"ِن قَبۡلِ أَن يَأۡتِيَ أَحَدَكُمُ ٱلۡمَوۡتُ فَيَقُولَ رَبِّ لَوۡلَا"],[-1,"ٓ"],[0," أَخَّرۡتَنِي"],[-1,"ٓ"],[0," إِلَىٰ"],[-1,"ٓ"],[0," أَجَلٖ قَرِيبٖ فَأَصَّدَّقَ وَأَكُن مِّنَ ٱلصَّٰلِحِينَ وَلَن يُؤَخِّرَ ٱللَّهُ نَفۡسًا إِذَا جَآءَ "],[-1,"أَ"],[1,"ا"],[0,"جَلُهَا وَٱللَّهُ خَبِيرُ بِمَا تَعۡمَلُونَ"]]},"hafsVSbazzi":{"diffCount":58,"diffs":[[0,"إِذَا جَآءَكَ ٱلۡمُنَٰفِقُونَ قَالُواْ نَشۡهَدُ إِنَّكَ لَرَسُولُ ٱللَّهِ وَٱللَّهُ يَعۡلَمُ إِنَّكَ لَرَسُولُهُ وَٱللَّهُ يَشۡهَدُ إِنَّ ٱلۡمُنَٰفِقِينَ لَكَٰذِبُونَ ٱتَّخَذُو"],[-1,"ٓ"],[0,"اْ أَيۡمَٰنَهُم"],[-1,"ۡ"],[1,"ُ"],[0," جُنَّةٗ فَصَدُّواْ عَن سَبِيلِ ٱللَّهِ إِنَّهُم"],[-1,"ۡ"],[1,"ُ"],[0," سَآءَ مَا كَانُواْ يَعۡمَلُونَ ذَٰلِكَ بِأَنَّهُم"],[-1,"ۡ"],[1,"ُ"],[0," ءَامَنُواْ ثُمَّ كَفَرُواْ فَطُبِعَ عَلَىٰ قُلُوبِهِم"],[-1,"ۡ"],[1,"ُ"],[0," فَهُم"],[-1,"ۡ"],[1,"ُ"],[0," لَا يَفۡقَهُونَ وَإِذَا رَأَيۡتَهُم"],[-1,"ۡ"],[1,"ُ"],[0," تُعۡجِبُكَ أَجۡسَامُهُم"],[-1,"ۡ"],[1,"ُ"],[0," وَإِن يَقُولُواْ تَسۡمَعۡ لِقَوۡلِهِم"],[-1,"ۡ"],[1,"ُ"],[0," كَأَنَّهُم"],[-1,"ۡ"],[1,"ُ"],[0," خُشُبٞ مُّسَنَّدَةٞ يَحۡس"],[-1,"َ"],[1,"ِ"],[0,"بُونَ كُلَّ صَيۡحَةٍ عَلَيۡهِم"],[-1,"ۡ"],[1,"ُ"],[0," هُمُ ٱلۡعَدُوُّ فَٱحۡذَرۡهُم"],[-1,"ۡ"],[1,"ُ"],[0," قَٰتَلَهُمُ ٱللَّهُ أَنَّىٰ يُؤۡفَكُونَ وَإِذَا قِيلَ لَهُم"],[-1,"ۡ"],[1,"ُ"],[0," تَعَالَوۡاْ يَسۡتَغۡفِرۡ لَكُم"],[-1,"ۡ"],[1,"ُ"],[0," رَسُولُ ٱللَّهِ لَوَّوۡاْ رُءُوسَهُم"],[-1,"ۡ"],[1,"ُ"],[0," وَرَأَيۡتَهُم"],[-1,"ۡ"],[1,"ُ"],[0," يَصُدُّونَ وَهُم"],[1,"ُ"],[0," م"],[-1,"ّ"],[0,"ُسۡتَكۡبِرُونَ سَوَآءٌ عَلَيۡهِم"],[-1,"ۡ"],[1,"ُ"],[0," أَسۡتَغۡفَرۡتَ لَهُم"],[-1,"ۡ"],[1,"ُ"],[0," أَمۡ لَمۡ تَسۡتَغۡفِرۡ لَهُم"],[-1,"ۡ"],[1,"ُ"],[0," لَن يَغۡفِرَ ٱللَّهُ لَهُم"],[-1,"ۡ"],[1,"ُ"],[0," إِنَّ ٱللَّهَ لَا يَهۡدِي ٱلۡقَوۡمَ ٱلۡفَٰسِقِينَ هُمُ ٱلَّذِينَ يَقُولُونَ لَا تُنفِقُواْ عَلَىٰ مَنۡ عِندَ رَسُولِ ٱللَّهِ حَتَّىٰ يَنفَضُّواْ وَلِلَّهِ خَزَآئِنُ ٱلسَّمَٰوَٰتِ وَٱلۡأَرۡضِ وَلَٰكِنَّ ٱلۡمُنَٰفِقِينَ لَا يَفۡقَهُونَ يَقُولُونَ لَئِن رَّجَعۡنَا"],[-1,"ٓ"],[0," إِلَى ٱلۡمَدِينَةِ لَيُخۡرِجَنَّ ٱلۡأَعَزُّ مِنۡهَا ٱلۡأَذَلَّ وَلِلَّهِ ٱلۡعِزَّةُ وَلِرَسُولِهِ وَلِلۡمُؤۡمِنِينَ وَلَٰكِنَّ ٱلۡمُنَٰفِقِينَ لَا يَعۡلَمُونَ يَٰ"],[-1,"ٓ"],[0,"أَيُّهَا ٱلَّذِينَ ءَامَنُواْ لَا تُلۡهِكُم"],[-1,"ۡ"],[1,"ُ"],[0," أَمۡوَٰلُكُم"],[-1,"ۡ"],[1,"ُ"],[0," وَلَا"],[-1,"ٓ"],[0," أَوۡلَٰدُكُم"],[-1,"ۡ"],[1,"ُ"],[0," عَن ذِكۡرِ ٱللَّهِ وَمَن يَفۡعَلۡ ذَٰلِكَ فَأُوْلَٰٓئِكَ هُمُ ٱلۡخَٰسِرُونَ وَأَنفِقُواْ مِن مَّا رَزَقۡنَٰكُم"],[1,"ُ"],[0," م"],[-1,"ّ"],[0,"ِن قَبۡلِ أَن يَأۡتِيَ أَحَدَكُمُ ٱلۡمَوۡتُ فَيَقُولَ رَبِّ لَوۡلَا"],[-1,"ٓ"],[0," أَخَّرۡتَنِي"],[-1,"ٓ"],[0," إِلَىٰ"],[-1,"ٓ"],[0," أَجَلٖ قَرِيبٖ فَأَصَّدَّقَ وَأَكُن مِّنَ ٱلصَّٰلِحِينَ وَلَن يُؤَخِّرَ ٱللَّهُ نَفۡسًا إِذَا جَا"],[-1,"ٓءَ"],[0," أَجَلُهَا وَٱللَّهُ خَبِيرُ بِمَا تَعۡمَلُونَ"]]}}